gemini_cli_mcp/__init__.py
gemini_cli_mcp/server.py
gemini_cli_mcp_async-0.1.0.dist-info/licenses/LICENSE
gemini_cli_mcp_async-0.1.0.dist-info/METADATA
gemini_cli_mcp_async-0.1.0.dist-info/WHEEL
gemini_cli_mcp_async-0.1.0.dist-info/entry_points.txt
gemini_cli_mcp_async-0.1.0.dist-info/top_level.txt
gemini_cli_mcp_async-0.1.0.dist-info/RECORD
