Metadata-Version: 2.4
Name: gemini-cli-mcp-async
Version: 0.1.0
Summary: Async wrapper for Gemini CLI to enable parallel task execution in Claude Code
Author-email: User <user@example.com>
License: MIT
Project-URL: Homepage, https://github.com/your-username/gemini-cli-mcp
Project-URL: Repository, https://github.com/your-username/gemini-cli-mcp.git
Project-URL: Issues, https://github.com/your-username/gemini-cli-mcp/issues
Keywords: gemini,cli,mcp,async,claude
Classifier: Development Status :: 4 - Beta
Classifier: Intended Audience :: Developers
Classifier: License :: OSI Approved :: MIT License
Classifier: Programming Language :: Python :: 3
Classifier: Programming Language :: Python :: 3.8
Classifier: Programming Language :: Python :: 3.9
Classifier: Programming Language :: Python :: 3.10
Classifier: Programming Language :: Python :: 3.11
Classifier: Programming Language :: Python :: 3.12
Classifier: Topic :: Software Development :: Libraries :: Python Modules
Classifier: Topic :: Utilities
Requires-Python: >=3.8
License-File: LICENSE
Provides-Extra: dev
Requires-Dist: pytest>=7.0; extra == "dev"
Requires-Dist: black>=22.0; extra == "dev"
Requires-Dist: isort>=5.0; extra == "dev"
Requires-Dist: flake8>=4.0; extra == "dev"
Dynamic: license-file
